{"nodes": [{"id": "c_users_turha_desktop_dev_ops_new_07_devtools_productivity_cli_tools_r_ai_os_src_cortex_store_rs", "label": "store.rs", "file_type": "code", "source_file": "C:\\Users\\turha\\Desktop\\Dev_Ops_New\\07_DevTools_&_Productivity\\CLI_Tools\\R-AI-OS\\src\\cortex\\store.rs", "source_location": "L1"}, {"id": "cortex_store_store_path", "label": "store_path()", "file_type": "code", "source_file": "C:\\Users\\turha\\Desktop\\Dev_Ops_New\\07_DevTools_&_Productivity\\CLI_Tools\\R-AI-OS\\src\\cortex\\store.rs", "source_location": "L18"}, {"id": "cortex_store_embpoint", "label": "EmbPoint", "file_type": "code", "source_file": "C:\\Users\\turha\\Desktop\\Dev_Ops_New\\07_DevTools_&_Productivity\\CLI_Tools\\R-AI-OS\\src\\cortex\\store.rs", "source_location": "L28"}, {"id": "cortex_store_embpoint_distance", "label": ".distance()", "file_type": "code", "source_file": "C:\\Users\\turha\\Desktop\\Dev_Ops_New\\07_DevTools_&_Productivity\\CLI_Tools\\R-AI-OS\\src\\cortex\\store.rs", "source_location": "L31"}, {"id": "cortex_store_chunkmeta", "label": "ChunkMeta", "file_type": "code", "source_file": "C:\\Users\\turha\\Desktop\\Dev_Ops_New\\07_DevTools_&_Productivity\\CLI_Tools\\R-AI-OS\\src\\cortex\\store.rs", "source_location": "L40"}, {"id": "cortex_store_vectorresult", "label": "VectorResult", "file_type": "code", "source_file": "C:\\Users\\turha\\Desktop\\Dev_Ops_New\\07_DevTools_&_Productivity\\CLI_Tools\\R-AI-OS\\src\\cortex\\store.rs", "source_location": "L48"}, {"id": "cortex_store_persistedstore", "label": "PersistedStore", "file_type": "code", "source_file": "C:\\Users\\turha\\Desktop\\Dev_Ops_New\\07_DevTools_&_Productivity\\CLI_Tools\\R-AI-OS\\src\\cortex\\store.rs", "source_location": "L59"}, {"id": "cortex_store_vectorengine", "label": "VectorEngine", "file_type": "code", "source_file": "C:\\Users\\turha\\Desktop\\Dev_Ops_New\\07_DevTools_&_Productivity\\CLI_Tools\\R-AI-OS\\src\\cortex\\store.rs", "source_location": "L69"}, {"id": "cortex_store_vectorengine_load", "label": ".load()", "file_type": "code", "source_file": "C:\\Users\\turha\\Desktop\\Dev_Ops_New\\07_DevTools_&_Productivity\\CLI_Tools\\R-AI-OS\\src\\cortex\\store.rs", "source_location": "L80"}, {"id": "cortex_store_vectorengine_save", "label": ".save()", "file_type": "code", "source_file": "C:\\Users\\turha\\Desktop\\Dev_Ops_New\\07_DevTools_&_Productivity\\CLI_Tools\\R-AI-OS\\src\\cortex\\store.rs", "source_location": "L112"}, {"id": "cortex_store_vectorengine_is_indexed", "label": ".is_indexed()", "file_type": "code", "source_file": "C:\\Users\\turha\\Desktop\\Dev_Ops_New\\07_DevTools_&_Productivity\\CLI_Tools\\R-AI-OS\\src\\cortex\\store.rs", "source_location": "L130"}, {"id": "cortex_store_vectorengine_upsert_file", "label": ".upsert_file()", "file_type": "code", "source_file": "C:\\Users\\turha\\Desktop\\Dev_Ops_New\\07_DevTools_&_Productivity\\CLI_Tools\\R-AI-OS\\src\\cortex\\store.rs", "source_location": "L135"}, {"id": "cortex_store_vectorengine_rebuild_hnsw", "label": ".rebuild_hnsw()", "file_type": "code", "source_file": "C:\\Users\\turha\\Desktop\\Dev_Ops_New\\07_DevTools_&_Productivity\\CLI_Tools\\R-AI-OS\\src\\cortex\\store.rs", "source_location": "L171"}, {"id": "cortex_store_vectorengine_query", "label": ".query()", "file_type": "code", "source_file": "C:\\Users\\turha\\Desktop\\Dev_Ops_New\\07_DevTools_&_Productivity\\CLI_Tools\\R-AI-OS\\src\\cortex\\store.rs", "source_location": "L182"}, {"id": "cortex_store_vectorengine_chunk_count", "label": ".chunk_count()", "file_type": "code", "source_file": "C:\\Users\\turha\\Desktop\\Dev_Ops_New\\07_DevTools_&_Productivity\\CLI_Tools\\R-AI-OS\\src\\cortex\\store.rs", "source_location": "L209"}, {"id": "cortex_store_vectorengine_file_count", "label": ".file_count()", "file_type": "code", "source_file": "C:\\Users\\turha\\Desktop\\Dev_Ops_New\\07_DevTools_&_Productivity\\CLI_Tools\\R-AI-OS\\src\\cortex\\store.rs", "source_location": "L210"}, {"id": "cortex_store_vec_to_array", "label": "vec_to_array()", "file_type": "code", "source_file": "C:\\Users\\turha\\Desktop\\Dev_Ops_New\\07_DevTools_&_Productivity\\CLI_Tools\\R-AI-OS\\src\\cortex\\store.rs", "source_location": "L215"}], "edges": [{"source": "c_users_turha_desktop_dev_ops_new_07_devtools_productivity_cli_tools_r_ai_os_src_cortex_store_rs", "target": "pathbuf", "relation": "imports_from", "confidence": "EXTRACTED", "source_file": "C:\\Users\\turha\\Desktop\\Dev_Ops_New\\07_DevTools_&_Productivity\\CLI_Tools\\R-AI-OS\\src\\cortex\\store.rs", "source_location": "L10", "weight": 1.0, "context": "import"}, {"source": "c_users_turha_desktop_dev_ops_new_07_devtools_productivity_cli_tools_r_ai_os_src_cortex_store_rs", "target": "hashmap", "relation": "imports_from", "confidence": "EXTRACTED", "source_file": "C:\\Users\\turha\\Desktop\\Dev_Ops_New\\07_DevTools_&_Productivity\\CLI_Tools\\R-AI-OS\\src\\cortex\\store.rs", "source_location": "L11", "weight": 1.0, "context": "import"}, {"source": "c_users_turha_desktop_dev_ops_new_07_devtools_productivity_cli_tools_r_ai_os_src_cortex_store_rs", "target": "instant_distance", "relation": "imports_from", "confidence": "EXTRACTED", "source_file": "C:\\Users\\turha\\Desktop\\Dev_Ops_New\\07_DevTools_&_Productivity\\CLI_Tools\\R-AI-OS\\src\\cortex\\store.rs", "source_location": "L12", "weight": 1.0, "context": "import"}, {"source": "c_users_turha_desktop_dev_ops_new_07_devtools_productivity_cli_tools_r_ai_os_src_cortex_store_rs", "target": "serde", "relation": "imports_from", "confidence": "EXTRACTED", "source_file": "C:\\Users\\turha\\Desktop\\Dev_Ops_New\\07_DevTools_&_Productivity\\CLI_Tools\\R-AI-OS\\src\\cortex\\store.rs", "source_location": "L13", "weight": 1.0, "context": "import"}, {"source": "c_users_turha_desktop_dev_ops_new_07_devtools_productivity_cli_tools_r_ai_os_src_cortex_store_rs", "target": "embedder", "relation": "imports_from", "confidence": "EXTRACTED", "source_file": "C:\\Users\\turha\\Desktop\\Dev_Ops_New\\07_DevTools_&_Productivity\\CLI_Tools\\R-AI-OS\\src\\cortex\\store.rs", "source_location": "L14", "weight": 1.0, "context": "import"}, {"source": "c_users_turha_desktop_dev_ops_new_07_devtools_productivity_cli_tools_r_ai_os_src_cortex_store_rs", "target": "cortex_store_store_path", "relation": "contains", "confidence": "EXTRACTED", "source_file": "C:\\Users\\turha\\Desktop\\Dev_Ops_New\\07_DevTools_&_Productivity\\CLI_Tools\\R-AI-OS\\src\\cortex\\store.rs", "source_location": "L18", "weight": 1.0}, {"source": "c_users_turha_desktop_dev_ops_new_07_devtools_productivity_cli_tools_r_ai_os_src_cortex_store_rs", "target": "cortex_store_embpoint", "relation": "contains", "confidence": "EXTRACTED", "source_file": "C:\\Users\\turha\\Desktop\\Dev_Ops_New\\07_DevTools_&_Productivity\\CLI_Tools\\R-AI-OS\\src\\cortex\\store.rs", "source_location": "L28", "weight": 1.0}, {"source": "cortex_store_embpoint", "target": "cortex_store_embpoint_distance", "relation": "method", "confidence": "EXTRACTED", "source_file": "C:\\Users\\turha\\Desktop\\Dev_Ops_New\\07_DevTools_&_Productivity\\CLI_Tools\\R-AI-OS\\src\\cortex\\store.rs", "source_location": "L31", "weight": 1.0}, {"source": "c_users_turha_desktop_dev_ops_new_07_devtools_productivity_cli_tools_r_ai_os_src_cortex_store_rs", "target": "cortex_store_chunkmeta", "relation": "contains", "confidence": "EXTRACTED", "source_file": "C:\\Users\\turha\\Desktop\\Dev_Ops_New\\07_DevTools_&_Productivity\\CLI_Tools\\R-AI-OS\\src\\cortex\\store.rs", "source_location": "L40", "weight": 1.0}, {"source": "c_users_turha_desktop_dev_ops_new_07_devtools_productivity_cli_tools_r_ai_os_src_cortex_store_rs", "target": "cortex_store_vectorresult", "relation": "contains", "confidence": "EXTRACTED", "source_file": "C:\\Users\\turha\\Desktop\\Dev_Ops_New\\07_DevTools_&_Productivity\\CLI_Tools\\R-AI-OS\\src\\cortex\\store.rs", "source_location": "L48", "weight": 1.0}, {"source": "c_users_turha_desktop_dev_ops_new_07_devtools_productivity_cli_tools_r_ai_os_src_cortex_store_rs", "target": "cortex_store_persistedstore", "relation": "contains", "confidence": "EXTRACTED", "source_file": "C:\\Users\\turha\\Desktop\\Dev_Ops_New\\07_DevTools_&_Productivity\\CLI_Tools\\R-AI-OS\\src\\cortex\\store.rs", "source_location": "L59", "weight": 1.0}, {"source": "c_users_turha_desktop_dev_ops_new_07_devtools_productivity_cli_tools_r_ai_os_src_cortex_store_rs", "target": "cortex_store_vectorengine", "relation": "contains", "confidence": "EXTRACTED", "source_file": "C:\\Users\\turha\\Desktop\\Dev_Ops_New\\07_DevTools_&_Productivity\\CLI_Tools\\R-AI-OS\\src\\cortex\\store.rs", "source_location": "L69", "weight": 1.0}, {"source": "cortex_store_vectorengine", "target": "cortex_store_vectorengine_load", "relation": "method", "confidence": "EXTRACTED", "source_file": "C:\\Users\\turha\\Desktop\\Dev_Ops_New\\07_DevTools_&_Productivity\\CLI_Tools\\R-AI-OS\\src\\cortex\\store.rs", "source_location": "L80", "weight": 1.0}, {"source": "cortex_store_vectorengine", "target": "cortex_store_vectorengine_save", "relation": "method", "confidence": "EXTRACTED", "source_file": "C:\\Users\\turha\\Desktop\\Dev_Ops_New\\07_DevTools_&_Productivity\\CLI_Tools\\R-AI-OS\\src\\cortex\\store.rs", "source_location": "L112", "weight": 1.0}, {"source": "cortex_store_vectorengine", "target": "cortex_store_vectorengine_is_indexed", "relation": "method", "confidence": "EXTRACTED", "source_file": "C:\\Users\\turha\\Desktop\\Dev_Ops_New\\07_DevTools_&_Productivity\\CLI_Tools\\R-AI-OS\\src\\cortex\\store.rs", "source_location": "L130", "weight": 1.0}, {"source": "cortex_store_vectorengine", "target": "cortex_store_vectorengine_upsert_file", "relation": "method", "confidence": "EXTRACTED", "source_file": "C:\\Users\\turha\\Desktop\\Dev_Ops_New\\07_DevTools_&_Productivity\\CLI_Tools\\R-AI-OS\\src\\cortex\\store.rs", "source_location": "L135", "weight": 1.0}, {"source": "cortex_store_vectorengine", "target": "cortex_store_vectorengine_rebuild_hnsw", "relation": "method", "confidence": "EXTRACTED", "source_file": "C:\\Users\\turha\\Desktop\\Dev_Ops_New\\07_DevTools_&_Productivity\\CLI_Tools\\R-AI-OS\\src\\cortex\\store.rs", "source_location": "L171", "weight": 1.0}, {"source": "cortex_store_vectorengine", "target": "cortex_store_vectorengine_query", "relation": "method", "confidence": "EXTRACTED", "source_file": "C:\\Users\\turha\\Desktop\\Dev_Ops_New\\07_DevTools_&_Productivity\\CLI_Tools\\R-AI-OS\\src\\cortex\\store.rs", "source_location": "L182", "weight": 1.0}, {"source": "cortex_store_vectorengine", "target": "cortex_store_vectorengine_chunk_count", "relation": "method", "confidence": "EXTRACTED", "source_file": "C:\\Users\\turha\\Desktop\\Dev_Ops_New\\07_DevTools_&_Productivity\\CLI_Tools\\R-AI-OS\\src\\cortex\\store.rs", "source_location": "L209", "weight": 1.0}, {"source": "cortex_store_vectorengine", "target": "cortex_store_vectorengine_file_count", "relation": "method", "confidence": "EXTRACTED", "source_file": "C:\\Users\\turha\\Desktop\\Dev_Ops_New\\07_DevTools_&_Productivity\\CLI_Tools\\R-AI-OS\\src\\cortex\\store.rs", "source_location": "L210", "weight": 1.0}, {"source": "c_users_turha_desktop_dev_ops_new_07_devtools_productivity_cli_tools_r_ai_os_src_cortex_store_rs", "target": "cortex_store_vec_to_array", "relation": "contains", "confidence": "EXTRACTED", "source_file": "C:\\Users\\turha\\Desktop\\Dev_Ops_New\\07_DevTools_&_Productivity\\CLI_Tools\\R-AI-OS\\src\\cortex\\store.rs", "source_location": "L215", "weight": 1.0}, {"source": "cortex_store_vectorengine_load", "target": "cortex_store_store_path", "relation": "calls", "context": "call", "confidence": "EXTRACTED", "source_file": "C:\\Users\\turha\\Desktop\\Dev_Ops_New\\07_DevTools_&_Productivity\\CLI_Tools\\R-AI-OS\\src\\cortex\\store.rs", "source_location": "L81", "weight": 1.0}, {"source": "cortex_store_vectorengine_load", "target": "cortex_store_vec_to_array", "relation": "calls", "context": "call", "confidence": "EXTRACTED", "source_file": "C:\\Users\\turha\\Desktop\\Dev_Ops_New\\07_DevTools_&_Productivity\\CLI_Tools\\R-AI-OS\\src\\cortex\\store.rs", "source_location": "L87", "weight": 1.0}, {"source": "cortex_store_vectorengine_load", "target": "cortex_store_vectorengine_rebuild_hnsw", "relation": "calls", "context": "call", "confidence": "EXTRACTED", "source_file": "C:\\Users\\turha\\Desktop\\Dev_Ops_New\\07_DevTools_&_Productivity\\CLI_Tools\\R-AI-OS\\src\\cortex\\store.rs", "source_location": "L97", "weight": 1.0}, {"source": "cortex_store_vectorengine_save", "target": "cortex_store_store_path", "relation": "calls", "context": "call", "confidence": "EXTRACTED", "source_file": "C:\\Users\\turha\\Desktop\\Dev_Ops_New\\07_DevTools_&_Productivity\\CLI_Tools\\R-AI-OS\\src\\cortex\\store.rs", "source_location": "L114", "weight": 1.0}, {"source": "cortex_store_vectorengine_upsert_file", "target": "cortex_store_vectorengine_rebuild_hnsw", "relation": "calls", "context": "call", "confidence": "EXTRACTED", "source_file": "C:\\Users\\turha\\Desktop\\Dev_Ops_New\\07_DevTools_&_Productivity\\CLI_Tools\\R-AI-OS\\src\\cortex\\store.rs", "source_location": "L168", "weight": 1.0}, {"source": "cortex_store_vectorengine_rebuild_hnsw", "target": "cortex_store_embpoint", "relation": "calls", "context": "call", "confidence": "EXTRACTED", "source_file": "C:\\Users\\turha\\Desktop\\Dev_Ops_New\\07_DevTools_&_Productivity\\CLI_Tools\\R-AI-OS\\src\\cortex\\store.rs", "source_location": "L176", "weight": 1.0}, {"source": "cortex_store_vectorengine_query", "target": "cortex_store_embpoint", "relation": "calls", "context": "call", "confidence": "EXTRACTED", "source_file": "C:\\Users\\turha\\Desktop\\Dev_Ops_New\\07_DevTools_&_Productivity\\CLI_Tools\\R-AI-OS\\src\\cortex\\store.rs", "source_location": "L185", "weight": 1.0}, {"source": "cortex_store_vectorengine_query", "target": "cortex_store_embpoint_distance", "relation": "calls", "context": "call", "confidence": "EXTRACTED", "source_file": "C:\\Users\\turha\\Desktop\\Dev_Ops_New\\07_DevTools_&_Productivity\\CLI_Tools\\R-AI-OS\\src\\cortex\\store.rs", "source_location": "L193", "weight": 1.0}], "raw_calls": [{"caller_nid": "cortex_store_store_path", "callee": "join", "is_member_call": true, "source_file": "C:\\Users\\turha\\Desktop\\Dev_Ops_New\\07_DevTools_&_Productivity\\CLI_Tools\\R-AI-OS\\src\\cortex\\store.rs", "source_location": "L19"}, {"caller_nid": "cortex_store_store_path", "callee": "join", "is_member_call": true, "source_file": "C:\\Users\\turha\\Desktop\\Dev_Ops_New\\07_DevTools_&_Productivity\\CLI_Tools\\R-AI-OS\\src\\cortex\\store.rs", "source_location": "L19"}, {"caller_nid": "cortex_store_store_path", "callee": "unwrap_or_else", "is_member_call": true, "source_file": "C:\\Users\\turha\\Desktop\\Dev_Ops_New\\07_DevTools_&_Productivity\\CLI_Tools\\R-AI-OS\\src\\cortex\\store.rs", "source_location": "L19"}, {"caller_nid": "cortex_store_store_path", "callee": "config_dir", "is_member_call": false, "source_file": "C:\\Users\\turha\\Desktop\\Dev_Ops_New\\07_DevTools_&_Productivity\\CLI_Tools\\R-AI-OS\\src\\cortex\\store.rs", "source_location": "L19"}, {"caller_nid": "cortex_store_store_path", "callee": "from", "is_member_call": false, "source_file": "C:\\Users\\turha\\Desktop\\Dev_Ops_New\\07_DevTools_&_Productivity\\CLI_Tools\\R-AI-OS\\src\\cortex\\store.rs", "source_location": "L20"}, {"caller_nid": "cortex_store_embpoint_distance", "callee": "sum", "is_member_call": true, "source_file": "C:\\Users\\turha\\Desktop\\Dev_Ops_New\\07_DevTools_&_Productivity\\CLI_Tools\\R-AI-OS\\src\\cortex\\store.rs", "source_location": "L32"}, {"caller_nid": "cortex_store_embpoint_distance", "callee": "map", "is_member_call": true, "source_file": "C:\\Users\\turha\\Desktop\\Dev_Ops_New\\07_DevTools_&_Productivity\\CLI_Tools\\R-AI-OS\\src\\cortex\\store.rs", "source_location": "L32"}, {"caller_nid": "cortex_store_embpoint_distance", "callee": "zip", "is_member_call": true, "source_file": "C:\\Users\\turha\\Desktop\\Dev_Ops_New\\07_DevTools_&_Productivity\\CLI_Tools\\R-AI-OS\\src\\cortex\\store.rs", "source_location": "L32"}, {"caller_nid": "cortex_store_embpoint_distance", "callee": "iter", "is_member_call": true, "source_file": "C:\\Users\\turha\\Desktop\\Dev_Ops_New\\07_DevTools_&_Productivity\\CLI_Tools\\R-AI-OS\\src\\cortex\\store.rs", "source_location": "L32"}, {"caller_nid": "cortex_store_embpoint_distance", "callee": "iter", "is_member_call": true, "source_file": "C:\\Users\\turha\\Desktop\\Dev_Ops_New\\07_DevTools_&_Productivity\\CLI_Tools\\R-AI-OS\\src\\cortex\\store.rs", "source_location": "L32"}, {"caller_nid": "cortex_store_embpoint_distance", "callee": "clamp", "is_member_call": true, "source_file": "C:\\Users\\turha\\Desktop\\Dev_Ops_New\\07_DevTools_&_Productivity\\CLI_Tools\\R-AI-OS\\src\\cortex\\store.rs", "source_location": "L33"}, {"caller_nid": "cortex_store_vectorengine_load", "callee": "read", "is_member_call": false, "source_file": "C:\\Users\\turha\\Desktop\\Dev_Ops_New\\07_DevTools_&_Productivity\\CLI_Tools\\R-AI-OS\\src\\cortex\\store.rs", "source_location": "L82"}, {"caller_nid": "cortex_store_vectorengine_load", "callee": "collect", "is_member_call": true, "source_file": "C:\\Users\\turha\\Desktop\\Dev_Ops_New\\07_DevTools_&_Productivity\\CLI_Tools\\R-AI-OS\\src\\cortex\\store.rs", "source_location": "L84"}, {"caller_nid": "cortex_store_vectorengine_load", "callee": "map", "is_member_call": true, "source_file": "C:\\Users\\turha\\Desktop\\Dev_Ops_New\\07_DevTools_&_Productivity\\CLI_Tools\\R-AI-OS\\src\\cortex\\store.rs", "source_location": "L84"}, {"caller_nid": "cortex_store_vectorengine_load", "callee": "iter", "is_member_call": true, "source_file": "C:\\Users\\turha\\Desktop\\Dev_Ops_New\\07_DevTools_&_Productivity\\CLI_Tools\\R-AI-OS\\src\\cortex\\store.rs", "source_location": "L84"}, {"caller_nid": "cortex_store_vectorengine_load", "callee": "new", "is_member_call": false, "source_file": "C:\\Users\\turha\\Desktop\\Dev_Ops_New\\07_DevTools_&_Productivity\\CLI_Tools\\R-AI-OS\\src\\cortex\\store.rs", "source_location": "L103"}, {"caller_nid": "cortex_store_vectorengine_load", "callee": "new", "is_member_call": false, "source_file": "C:\\Users\\turha\\Desktop\\Dev_Ops_New\\07_DevTools_&_Productivity\\CLI_Tools\\R-AI-OS\\src\\cortex\\store.rs", "source_location": "L104"}, {"caller_nid": "cortex_store_vectorengine_load", "callee": "new", "is_member_call": false, "source_file": "C:\\Users\\turha\\Desktop\\Dev_Ops_New\\07_DevTools_&_Productivity\\CLI_Tools\\R-AI-OS\\src\\cortex\\store.rs", "source_location": "L105"}, {"caller_nid": "cortex_store_vectorengine_save", "callee": "parent", "is_member_call": true, "source_file": "C:\\Users\\turha\\Desktop\\Dev_Ops_New\\07_DevTools_&_Productivity\\CLI_Tools\\R-AI-OS\\src\\cortex\\store.rs", "source_location": "L115"}, {"caller_nid": "cortex_store_vectorengine_save", "callee": "create_dir_all", "is_member_call": false, "source_file": "C:\\Users\\turha\\Desktop\\Dev_Ops_New\\07_DevTools_&_Productivity\\CLI_Tools\\R-AI-OS\\src\\cortex\\store.rs", "source_location": "L116"}, {"caller_nid": "cortex_store_vectorengine_save", "callee": "clone", "is_member_call": true, "source_file": "C:\\Users\\turha\\Desktop\\Dev_Ops_New\\07_DevTools_&_Productivity\\CLI_Tools\\R-AI-OS\\src\\cortex\\store.rs", "source_location": "L119"}, {"caller_nid": "cortex_store_vectorengine_save", "callee": "collect", "is_member_call": true, "source_file": "C:\\Users\\turha\\Desktop\\Dev_Ops_New\\07_DevTools_&_Productivity\\CLI_Tools\\R-AI-OS\\src\\cortex\\store.rs", "source_location": "L120"}, {"caller_nid": "cortex_store_vectorengine_save", "callee": "map", "is_member_call": true, "source_file": "C:\\Users\\turha\\Desktop\\Dev_Ops_New\\07_DevTools_&_Productivity\\CLI_Tools\\R-AI-OS\\src\\cortex\\store.rs", "source_location": "L120"}, {"caller_nid": "cortex_store_vectorengine_save", "callee": "iter", "is_member_call": true, "source_file": "C:\\Users\\turha\\Desktop\\Dev_Ops_New\\07_DevTools_&_Productivity\\CLI_Tools\\R-AI-OS\\src\\cortex\\store.rs", "source_location": "L120"}, {"caller_nid": "cortex_store_vectorengine_save", "callee": "to_vec", "is_member_call": true, "source_file": "C:\\Users\\turha\\Desktop\\Dev_Ops_New\\07_DevTools_&_Productivity\\CLI_Tools\\R-AI-OS\\src\\cortex\\store.rs", "source_location": "L120"}, {"caller_nid": "cortex_store_vectorengine_save", "callee": "clone", "is_member_call": true, "source_file": "C:\\Users\\turha\\Desktop\\Dev_Ops_New\\07_DevTools_&_Productivity\\CLI_Tools\\R-AI-OS\\src\\cortex\\store.rs", "source_location": "L121"}, {"caller_nid": "cortex_store_vectorengine_save", "callee": "to_string", "is_member_call": false, "source_file": "C:\\Users\\turha\\Desktop\\Dev_Ops_New\\07_DevTools_&_Productivity\\CLI_Tools\\R-AI-OS\\src\\cortex\\store.rs", "source_location": "L123"}, {"caller_nid": "cortex_store_vectorengine_save", "callee": "write", "is_member_call": false, "source_file": "C:\\Users\\turha\\Desktop\\Dev_Ops_New\\07_DevTools_&_Productivity\\CLI_Tools\\R-AI-OS\\src\\cortex\\store.rs", "source_location": "L124"}, {"caller_nid": "cortex_store_vectorengine_is_indexed", "callee": "copied", "is_member_call": true, "source_file": "C:\\Users\\turha\\Desktop\\Dev_Ops_New\\07_DevTools_&_Productivity\\CLI_Tools\\R-AI-OS\\src\\cortex\\store.rs", "source_location": "L131"}, {"caller_nid": "cortex_store_vectorengine_is_indexed", "callee": "get", "is_member_call": true, "source_file": "C:\\Users\\turha\\Desktop\\Dev_Ops_New\\07_DevTools_&_Productivity\\CLI_Tools\\R-AI-OS\\src\\cortex\\store.rs", "source_location": "L131"}, {"caller_nid": "cortex_store_vectorengine_is_indexed", "callee": "Some", "is_member_call": false, "source_file": "C:\\Users\\turha\\Desktop\\Dev_Ops_New\\07_DevTools_&_Productivity\\CLI_Tools\\R-AI-OS\\src\\cortex\\store.rs", "source_location": "L131"}, {"caller_nid": "cortex_store_vectorengine_upsert_file", "callee": "enumerate", "is_member_call": true, "source_file": "C:\\Users\\turha\\Desktop\\Dev_Ops_New\\07_DevTools_&_Productivity\\CLI_Tools\\R-AI-OS\\src\\cortex\\store.rs", "source_location": "L143"}, {"caller_nid": "cortex_store_vectorengine_upsert_file", "callee": "iter", "is_member_call": true, "source_file": "C:\\Users\\turha\\Desktop\\Dev_Ops_New\\07_DevTools_&_Productivity\\CLI_Tools\\R-AI-OS\\src\\cortex\\store.rs", "source_location": "L143"}, {"caller_nid": "cortex_store_vectorengine_upsert_file", "callee": "new", "is_member_call": false, "source_file": "C:\\Users\\turha\\Desktop\\Dev_Ops_New\\07_DevTools_&_Productivity\\CLI_Tools\\R-AI-OS\\src\\cortex\\store.rs", "source_location": "L148"}, {"caller_nid": "cortex_store_vectorengine_upsert_file", "callee": "new", "is_member_call": false, "source_file": "C:\\Users\\turha\\Desktop\\Dev_Ops_New\\07_DevTools_&_Productivity\\CLI_Tools\\R-AI-OS\\src\\cortex\\store.rs", "source_location": "L149"}, {"caller_nid": "cortex_store_vectorengine_upsert_file", "callee": "enumerate", "is_member_call": true, "source_file": "C:\\Users\\turha\\Desktop\\Dev_Ops_New\\07_DevTools_&_Productivity\\CLI_Tools\\R-AI-OS\\src\\cortex\\store.rs", "source_location": "L150"}, {"caller_nid": "cortex_store_vectorengine_upsert_file", "callee": "zip", "is_member_call": true, "source_file": "C:\\Users\\turha\\Desktop\\Dev_Ops_New\\07_DevTools_&_Productivity\\CLI_Tools\\R-AI-OS\\src\\cortex\\store.rs", "source_location": "L150"}, {"caller_nid": "cortex_store_vectorengine_upsert_file", "callee": "drain", "is_member_call": true, "source_file": "C:\\Users\\turha\\Desktop\\Dev_Ops_New\\07_DevTools_&_Productivity\\CLI_Tools\\R-AI-OS\\src\\cortex\\store.rs", "source_location": "L150"}, {"caller_nid": "cortex_store_vectorengine_upsert_file", "callee": "drain", "is_member_call": true, "source_file": "C:\\Users\\turha\\Desktop\\Dev_Ops_New\\07_DevTools_&_Productivity\\CLI_Tools\\R-AI-OS\\src\\cortex\\store.rs", "source_location": "L150"}, {"caller_nid": "cortex_store_vectorengine_upsert_file", "callee": "push", "is_member_call": true, "source_file": "C:\\Users\\turha\\Desktop\\Dev_Ops_New\\07_DevTools_&_Productivity\\CLI_Tools\\R-AI-OS\\src\\cortex\\store.rs", "source_location": "L152"}, {"caller_nid": "cortex_store_vectorengine_upsert_file", "callee": "push", "is_member_call": true, "source_file": "C:\\Users\\turha\\Desktop\\Dev_Ops_New\\07_DevTools_&_Productivity\\CLI_Tools\\R-AI-OS\\src\\cortex\\store.rs", "source_location": "L153"}, {"caller_nid": "cortex_store_vectorengine_upsert_file", "callee": "push", "is_member_call": true, "source_file": "C:\\Users\\turha\\Desktop\\Dev_Ops_New\\07_DevTools_&_Productivity\\CLI_Tools\\R-AI-OS\\src\\cortex\\store.rs", "source_location": "L159"}, {"caller_nid": "cortex_store_vectorengine_upsert_file", "callee": "push", "is_member_call": true, "source_file": "C:\\Users\\turha\\Desktop\\Dev_Ops_New\\07_DevTools_&_Productivity\\CLI_Tools\\R-AI-OS\\src\\cortex\\store.rs", "source_location": "L160"}, {"caller_nid": "cortex_store_vectorengine_upsert_file", "callee": "insert", "is_member_call": true, "source_file": "C:\\Users\\turha\\Desktop\\Dev_Ops_New\\07_DevTools_&_Productivity\\CLI_Tools\\R-AI-OS\\src\\cortex\\store.rs", "source_location": "L165"}, {"caller_nid": "cortex_store_vectorengine_upsert_file", "callee": "to_string", "is_member_call": true, "source_file": "C:\\Users\\turha\\Desktop\\Dev_Ops_New\\07_DevTools_&_Productivity\\CLI_Tools\\R-AI-OS\\src\\cortex\\store.rs", "source_location": "L165"}, {"caller_nid": "cortex_store_vectorengine_rebuild_hnsw", "callee": "is_empty", "is_member_call": true, "source_file": "C:\\Users\\turha\\Desktop\\Dev_Ops_New\\07_DevTools_&_Productivity\\CLI_Tools\\R-AI-OS\\src\\cortex\\store.rs", "source_location": "L172"}, {"caller_nid": "cortex_store_vectorengine_rebuild_hnsw", "callee": "collect", "is_member_call": true, "source_file": "C:\\Users\\turha\\Desktop\\Dev_Ops_New\\07_DevTools_&_Productivity\\CLI_Tools\\R-AI-OS\\src\\cortex\\store.rs", "source_location": "L176"}, {"caller_nid": "cortex_store_vectorengine_rebuild_hnsw", "callee": "map", "is_member_call": true, "source_file": "C:\\Users\\turha\\Desktop\\Dev_Ops_New\\07_DevTools_&_Productivity\\CLI_Tools\\R-AI-OS\\src\\cortex\\store.rs", "source_location": "L176"}, {"caller_nid": "cortex_store_vectorengine_rebuild_hnsw", "callee": "iter", "is_member_call": true, "source_file": "C:\\Users\\turha\\Desktop\\Dev_Ops_New\\07_DevTools_&_Productivity\\CLI_Tools\\R-AI-OS\\src\\cortex\\store.rs", "source_location": "L176"}, {"caller_nid": "cortex_store_vectorengine_rebuild_hnsw", "callee": "collect", "is_member_call": true, "source_file": "C:\\Users\\turha\\Desktop\\Dev_Ops_New\\07_DevTools_&_Productivity\\CLI_Tools\\R-AI-OS\\src\\cortex\\store.rs", "source_location": "L177"}, {"caller_nid": "cortex_store_vectorengine_rebuild_hnsw", "callee": "len", "is_member_call": true, "source_file": "C:\\Users\\turha\\Desktop\\Dev_Ops_New\\07_DevTools_&_Productivity\\CLI_Tools\\R-AI-OS\\src\\cortex\\store.rs", "source_location": "L177"}, {"caller_nid": "cortex_store_vectorengine_rebuild_hnsw", "callee": "Some", "is_member_call": false, "source_file": "C:\\Users\\turha\\Desktop\\Dev_Ops_New\\07_DevTools_&_Productivity\\CLI_Tools\\R-AI-OS\\src\\cortex\\store.rs", "source_location": "L178"}, {"caller_nid": "cortex_store_vectorengine_rebuild_hnsw", "callee": "build", "is_member_call": true, "source_file": "C:\\Users\\turha\\Desktop\\Dev_Ops_New\\07_DevTools_&_Productivity\\CLI_Tools\\R-AI-OS\\src\\cortex\\store.rs", "source_location": "L178"}, {"caller_nid": "cortex_store_vectorengine_rebuild_hnsw", "callee": "default", "is_member_call": false, "source_file": "C:\\Users\\turha\\Desktop\\Dev_Ops_New\\07_DevTools_&_Productivity\\CLI_Tools\\R-AI-OS\\src\\cortex\\store.rs", "source_location": "L178"}, {"caller_nid": "cortex_store_vectorengine_query", "callee": "default", "is_member_call": false, "source_file": "C:\\Users\\turha\\Desktop\\Dev_Ops_New\\07_DevTools_&_Productivity\\CLI_Tools\\R-AI-OS\\src\\cortex\\store.rs", "source_location": "L186"}, {"caller_nid": "cortex_store_vectorengine_query", "callee": "new", "is_member_call": false, "source_file": "C:\\Users\\turha\\Desktop\\Dev_Ops_New\\07_DevTools_&_Productivity\\CLI_Tools\\R-AI-OS\\src\\cortex\\store.rs", "source_location": "L187"}, {"caller_nid": "cortex_store_vectorengine_query", "callee": "search", "is_member_call": true, "source_file": "C:\\Users\\turha\\Desktop\\Dev_Ops_New\\07_DevTools_&_Productivity\\CLI_Tools\\R-AI-OS\\src\\cortex\\store.rs", "source_location": "L189"}, {"caller_nid": "cortex_store_vectorengine_query", "callee": "get", "is_member_call": true, "source_file": "C:\\Users\\turha\\Desktop\\Dev_Ops_New\\07_DevTools_&_Productivity\\CLI_Tools\\R-AI-OS\\src\\cortex\\store.rs", "source_location": "L191"}, {"caller_nid": "cortex_store_vectorengine_query", "callee": "clamp", "is_member_call": true, "source_file": "C:\\Users\\turha\\Desktop\\Dev_Ops_New\\07_DevTools_&_Productivity\\CLI_Tools\\R-AI-OS\\src\\cortex\\store.rs", "source_location": "L194"}, {"caller_nid": "cortex_store_vectorengine_query", "callee": "push", "is_member_call": true, "source_file": "C:\\Users\\turha\\Desktop\\Dev_Ops_New\\07_DevTools_&_Productivity\\CLI_Tools\\R-AI-OS\\src\\cortex\\store.rs", "source_location": "L195"}, {"caller_nid": "cortex_store_vectorengine_query", "callee": "clone", "is_member_call": true, "source_file": "C:\\Users\\turha\\Desktop\\Dev_Ops_New\\07_DevTools_&_Productivity\\CLI_Tools\\R-AI-OS\\src\\cortex\\store.rs", "source_location": "L196"}, {"caller_nid": "cortex_store_vectorengine_query", "callee": "clone", "is_member_call": true, "source_file": "C:\\Users\\turha\\Desktop\\Dev_Ops_New\\07_DevTools_&_Productivity\\CLI_Tools\\R-AI-OS\\src\\cortex\\store.rs", "source_location": "L198"}, {"caller_nid": "cortex_store_vectorengine_query", "callee": "len", "is_member_call": true, "source_file": "C:\\Users\\turha\\Desktop\\Dev_Ops_New\\07_DevTools_&_Productivity\\CLI_Tools\\R-AI-OS\\src\\cortex\\store.rs", "source_location": "L201"}, {"caller_nid": "cortex_store_vectorengine_query", "callee": "sort_by", "is_member_call": true, "source_file": "C:\\Users\\turha\\Desktop\\Dev_Ops_New\\07_DevTools_&_Productivity\\CLI_Tools\\R-AI-OS\\src\\cortex\\store.rs", "source_location": "L205"}, {"caller_nid": "cortex_store_vectorengine_query", "callee": "unwrap_or", "is_member_call": true, "source_file": "C:\\Users\\turha\\Desktop\\Dev_Ops_New\\07_DevTools_&_Productivity\\CLI_Tools\\R-AI-OS\\src\\cortex\\store.rs", "source_location": "L205"}, {"caller_nid": "cortex_store_vectorengine_query", "callee": "partial_cmp", "is_member_call": true, "source_file": "C:\\Users\\turha\\Desktop\\Dev_Ops_New\\07_DevTools_&_Productivity\\CLI_Tools\\R-AI-OS\\src\\cortex\\store.rs", "source_location": "L205"}, {"caller_nid": "cortex_store_vectorengine_chunk_count", "callee": "len", "is_member_call": true, "source_file": "C:\\Users\\turha\\Desktop\\Dev_Ops_New\\07_DevTools_&_Productivity\\CLI_Tools\\R-AI-OS\\src\\cortex\\store.rs", "source_location": "L209"}, {"caller_nid": "cortex_store_vectorengine_file_count", "callee": "len", "is_member_call": true, "source_file": "C:\\Users\\turha\\Desktop\\Dev_Ops_New\\07_DevTools_&_Productivity\\CLI_Tools\\R-AI-OS\\src\\cortex\\store.rs", "source_location": "L210"}, {"caller_nid": "cortex_store_vec_to_array", "callee": "min", "is_member_call": true, "source_file": "C:\\Users\\turha\\Desktop\\Dev_Ops_New\\07_DevTools_&_Productivity\\CLI_Tools\\R-AI-OS\\src\\cortex\\store.rs", "source_location": "L217"}, {"caller_nid": "cortex_store_vec_to_array", "callee": "len", "is_member_call": true, "source_file": "C:\\Users\\turha\\Desktop\\Dev_Ops_New\\07_DevTools_&_Productivity\\CLI_Tools\\R-AI-OS\\src\\cortex\\store.rs", "source_location": "L217"}, {"caller_nid": "cortex_store_vec_to_array", "callee": "copy_from_slice", "is_member_call": true, "source_file": "C:\\Users\\turha\\Desktop\\Dev_Ops_New\\07_DevTools_&_Productivity\\CLI_Tools\\R-AI-OS\\src\\cortex\\store.rs", "source_location": "L218"}]}